BotSAmino/__init__.py
BotSAmino/acm.py
BotSAmino/bot.py
BotSAmino/client.py
BotSAmino/local.py
BotSAmino/socket.py
BotSAmino/lib/__init__.py
BotSAmino/lib/exception.py
BotSAmino/lib/headers.py
BotSAmino/lib/objects.py
BotSAmino-1.0.4.dist-info/LICENSE
BotSAmino-1.0.4.dist-info/METADATA
BotSAmino-1.0.4.dist-info/WHEEL
BotSAmino-1.0.4.dist-info/top_level.txt
BotSAmino-1.0.4.dist-info/RECORD
