Metadata-Version: 2.1
Name: BotSAmino
Version: 1.0.4
Summary: Amino Bots with python!
Home-page: https://github.com/SirLez/BotSAmino
Author: SirLez
Author-email: SirLezDV@gmail.com
License: MIT
Download-URL: https://github.com/SirLez/BotSAmino/archive/refs/heads/main.zip
Keywords: aminoapps,amino-py,amino,amino-bot,narvii,api,python,python3,python3.x,ThePhoenix78,AminoBot,BotAmino,botamino,aminobot,botaminew,samino,SAmino,SirLez,sirlez
Platform: UNKNOWN
License-File: LICENSE
Requires-Dist: setuptools
Requires-Dist: requests
Requires-Dist: six
Requires-Dist: websocket-client
